ory_client/__init__.py
ory_client/api_client.py
ory_client/api_response.py
ory_client/configuration.py
ory_client/exceptions.py
ory_client/py.typed
ory_client/rest.py
ory_client/api/__init__.py
ory_client/api/courier_api.py
ory_client/api/events_api.py
ory_client/api/frontend_api.py
ory_client/api/identity_api.py
ory_client/api/jwk_api.py
ory_client/api/metadata_api.py
ory_client/api/o_auth2_api.py
ory_client/api/oidc_api.py
ory_client/api/permission_api.py
ory_client/api/project_api.py
ory_client/api/relationship_api.py
ory_client/api/wellknown_api.py
ory_client/api/workspace_api.py
ory_client/models/__init__.py
ory_client/models/accept_device_user_code_request.py
ory_client/models/accept_o_auth2_consent_request.py
ory_client/models/accept_o_auth2_consent_request_session.py
ory_client/models/accept_o_auth2_login_request.py
ory_client/models/account_experience_colors.py
ory_client/models/account_experience_configuration.py
ory_client/models/active_project_in_console.py
ory_client/models/add_project_to_workspace_body.py
ory_client/models/attribute.py
ory_client/models/attribute_filter.py
ory_client/models/attributes_count_datapoint.py
ory_client/models/authenticator_assurance_level.py
ory_client/models/basic_organization.py
ory_client/models/batch_check_permission_body.py
ory_client/models/batch_check_permission_result.py
ory_client/models/batch_patch_identities_response.py
ory_client/models/billing_period_bucket.py
ory_client/models/check_opl_syntax_result.py
ory_client/models/check_permission_result.py
ory_client/models/check_permission_result_with_error.py
ory_client/models/cloud_account.py
ory_client/models/consistency_request_parameters.py
ory_client/models/continue_with.py
ory_client/models/continue_with_recovery_ui.py
ory_client/models/continue_with_recovery_ui_flow.py
ory_client/models/continue_with_redirect_browser_to.py
ory_client/models/continue_with_set_ory_session_token.py
ory_client/models/continue_with_settings_ui.py
ory_client-1.22.22.dist-info/LICENSE
ory_client-1.22.22.dist-info/METADATA
ory_client-1.22.22.dist-info/WHEEL
ory_client-1.22.22.dist-info/top_level.txt
ory_client-1.22.22.dist-info/RECORD
