Metadata-Version: 2.1
Name: ory-client
Version: 1.22.22
Summary: Ory APIs
Home-page: https://github.com/ory/sdk
Author: API Support
Author-email: support@ory.sh
License: Apache 2.0
Keywords: OpenAPI,OpenAPI-Generator,Ory APIs
License-File: LICENSE
Requires-Dist: pydantic>=2
Requires-Dist: python-dateutil>=2.8.2
Requires-Dist: typing-extensions>=4.7.1
Requires-Dist: urllib3<3.0.0,>=1.25.3
